jupyterlite_xeus_nelson/__init__.py
jupyterlite_xeus_nelson/_version.py
jupyterlite_xeus_nelson/build.py
jupyterlite_xeus_nelson-0.1.4.data/data/share/jupyter/labextensions/@jupyterlite/xeus-nelson-kernel/install.json
jupyterlite_xeus_nelson-0.1.4.data/data/share/jupyter/labextensions/@jupyterlite/xeus-nelson-kernel/package.json
jupyterlite_xeus_nelson-0.1.4.data/data/share/jupyter/labextensions/@jupyterlite/xeus-nelson-kernel/static/213.f89a101850d49609bb95.js
jupyterlite_xeus_nelson-0.1.4.data/data/share/jupyter/labextensions/@jupyterlite/xeus-nelson-kernel/static/213.f89a101850d49609bb95.js.LICENSE.txt
jupyterlite_xeus_nelson-0.1.4.data/data/share/jupyter/labextensions/@jupyterlite/xeus-nelson-kernel/static/553002d543a9199df1e32348f99812205fb446205bd319f902ff7f8a27525f28.png
jupyterlite_xeus_nelson-0.1.4.data/data/share/jupyter/labextensions/@jupyterlite/xeus-nelson-kernel/static/69da0ac9a09126e3c01831219b74572f3b76533e342c72f8afa9fd8f01dcc8e8.png
jupyterlite_xeus_nelson-0.1.4.data/data/share/jupyter/labextensions/@jupyterlite/xeus-nelson-kernel/static/708.7d4632730c6b1fa3bea9.js
jupyterlite_xeus_nelson-0.1.4.data/data/share/jupyter/labextensions/@jupyterlite/xeus-nelson-kernel/static/747.b536d06e617484e9cba5.js
jupyterlite_xeus_nelson-0.1.4.data/data/share/jupyter/labextensions/@jupyterlite/xeus-nelson-kernel/static/870.a200ec1fdeec561413b1.js
jupyterlite_xeus_nelson-0.1.4.data/data/share/jupyter/labextensions/@jupyterlite/xeus-nelson-kernel/static/870.a200ec1fdeec561413b1.js.LICENSE.txt
jupyterlite_xeus_nelson-0.1.4.data/data/share/jupyter/labextensions/@jupyterlite/xeus-nelson-kernel/static/remoteEntry.1d3ddca10c4c40c38bea.js
jupyterlite_xeus_nelson-0.1.4.data/data/share/jupyter/labextensions/@jupyterlite/xeus-nelson-kernel/static/style.js
jupyterlite_xeus_nelson-0.1.4.data/data/share/jupyter/labextensions/@jupyterlite/xeus-nelson-kernel/static/third-party-licenses.json
jupyterlite_xeus_nelson-0.1.4.dist-info/LICENSE
jupyterlite_xeus_nelson-0.1.4.dist-info/METADATA
jupyterlite_xeus_nelson-0.1.4.dist-info/WHEEL
jupyterlite_xeus_nelson-0.1.4.dist-info/top_level.txt
jupyterlite_xeus_nelson-0.1.4.dist-info/RECORD
