Metadata-Version: 2.1
Name: jupyterlite-xeus-nelson
Version: 0.1.4
Summary: A Nelson kernel for JupyterLite, powered by Xeus
Home-page: https://github.com/jupyterlite/xeus-nelson-kernel
Author: JupyterLite Contributors
License: BSD-3-Clause
Keywords: Jupyter,JupyterLab,JupyterLab3
Platform: Linux
Platform: Mac OS X
Platform: Windows
Classifier: License :: OSI Approved :: BSD License
Classifier: Programming Language :: Python
Classifier: Programming Language :: Python :: 3
Classifier: Programming Language :: Python :: 3.6
Classifier: Programming Language :: Python :: 3.7
Classifier: Programming Language :: Python :: 3.8
Classifier: Programming Language :: Python :: 3.9
Classifier: Programming Language :: Python :: 3.10
Classifier: Programming Language :: Python :: 3.11
Classifier: Framework :: Jupyter
Classifier: Framework :: Jupyter :: JupyterLab
Classifier: Framework :: Jupyter :: JupyterLab :: 3
Classifier: Framework :: Jupyter :: JupyterLab :: Extensions
Classifier: Framework :: Jupyter :: JupyterLab :: Extensions :: Prebuilt
Requires-Python: >=3.8
License-File: LICENSE
Requires-Dist: traitlets
Requires-Dist: jupyterlite-core (>=0.1.0b20)
Requires-Dist: requests
Requires-Dist: empack (<3,>=2.0.9)
Requires-Dist: typer
